cnn_model_package/VERSION
cnn_model_package/__Init__.py
cnn_model_package/model.py
cnn_model_package/predict.py
cnn_model_package/train_model.py
cnn_model_package/config/__init__.py
cnn_model_package/config/core.py
cnn_model_package/datasets/__init__.py
cnn_model_package/datasets/test_data/0193.jpg
cnn_model_package/processing/__init__.py
cnn_model_package/processing/data_manager.py
cnn_model_package/processing/preprocessors.py
cnn_model_package/trained_models/__init__.py
cnn_model_package/trained_models/cnn_model_0.0.1.keras
kitchen_ware_classification_cnn_model-0.0.1.dist-info/METADATA
kitchen_ware_classification_cnn_model-0.0.1.dist-info/WHEEL
kitchen_ware_classification_cnn_model-0.0.1.dist-info/top_level.txt
kitchen_ware_classification_cnn_model-0.0.1.dist-info/RECORD
