Metadata-Version: 2.1
Name: kitchen_ware_classification_cnn_model
Version: 0.0.1
Summary: Convulational neural model package from Train In Data.
Home-page: https://github.com/chibuikeeugene/kitchen_ware_classification_cnn/
Author: Eugene
Author-email: chibuikeeugene@gmail.com
License: MIT
Classifier: License :: OSI Approved :: MIT License
Classifier: Programming Language :: Python
Classifier: Programming Language :: Python :: 3
Classifier: Programming Language :: Python :: 3.6
Classifier: Programming Language :: Python :: Implementation :: CPython
Classifier: Programming Language :: Python :: Implementation :: PyPy
Requires-Python: >=3.6.0
Requires-Dist: pandas ==2.2.1
Requires-Dist: numpy ==1.26.4
Requires-Dist: scikeras ==0.12.0
Requires-Dist: scikit-learn ==1.4.1
Requires-Dist: tensorflow ==2.16.1
Requires-Dist: glob
Requires-Dist: keras ==3.1.1
Requires-Dist: typing-extensions ==4.10.0
Requires-Dist: wheel ==0.43.0
Requires-Dist: setuptools ==58.1.0
Requires-Dist: pydantic ==2.6.4
Requires-Dist: kaggle ==1.5.1.1
Requires-Dist: pytest ==8.1.1
